README.txt
setup.cfg
setup.py
docs/HISTORY.txt
zopyx/__init__.py
zopyx.smartprintng.psd.egg-info/PKG-INFO
zopyx.smartprintng.psd.egg-info/SOURCES.txt
zopyx.smartprintng.psd.egg-info/dependency_links.txt
zopyx.smartprintng.psd.egg-info/entry_points.txt
zopyx.smartprintng.psd.egg-info/namespace_packages.txt
zopyx.smartprintng.psd.egg-info/not-zip-safe
zopyx.smartprintng.psd.egg-info/requires.txt
zopyx.smartprintng.psd.egg-info/top_level.txt
zopyx/smartprintng/__init__.py
zopyx/smartprintng/psd/__init__.py
zopyx/smartprintng/psd/psd.py