Metadata-Version: 1.0
Name: zopyx.smartprintng.psd
Version: 0.1.0
Summary: PSD -> PrinceXML converter
Home-page: http://pypi.python.org/pypi/zopyx.smartprintng.psd
Author: Andreas Jung
Author-email: info@zopyx.com
License: GPL 2
Platform: UNKNOWN
